unicorn_pwrs/__init__.py
unicorn_pwrs/unicorn_pwrs.py
unicorn_pwrs/data/cover.txt
unicorn_pwrs/data/cv.txt
unicorn_pwrs/data/reference.txt
unicorn_pwrs/data/unicorn_bleep.wav
unicorn_pwrs/data/unicorn_click.wav
unicorn_pwrs-0.1.dist-info/DESCRIPTION.rst
unicorn_pwrs-0.1.dist-info/METADATA
unicorn_pwrs-0.1.dist-info/RECORD
unicorn_pwrs-0.1.dist-info/WHEEL
unicorn_pwrs-0.1.dist-info/entry_points.txt
unicorn_pwrs-0.1.dist-info/metadata.json
unicorn_pwrs-0.1.dist-info/top_level.txt
